setup.py
ddlp_distributions/Binomialdistribution.py
ddlp_distributions/Gaussiandistribution.py
ddlp_distributions/Generaldistribution.py
ddlp_distributions/__init__.py
ddlp_distributions.egg-info/PKG-INFO
ddlp_distributions.egg-info/SOURCES.txt
ddlp_distributions.egg-info/dependency_links.txt
ddlp_distributions.egg-info/not-zip-safe
ddlp_distributions.egg-info/top_level.txt